[
	{
		"Index": 0,
		"JPN": [
			"えいぎょう{時間|じかん}<BREAK>ＡＭ９：００～ＡＭ０：００<BREAK>におこしください",
			"\f"
		]
	},
	{
		"Index": 1,
		"JPN": [
			"えいぎょう{時間|じかん}<BREAK>ＡＭ９：００～ＡＭ０：００<BREAK>におこしください",
			"\f"
		]
	},
	{
		"Index": 2,
		"JPN": [
			"えいぎょう{時間|じかん}<BREAK>ＡＭ９：００～ＡＭ０：００<BREAK>におこしください",
			"\f"
		]
	},
	{
		"Index": 3,
		"JPN": [
			"えいぎょう{時間|じかん}<BREAK>ＡＭ８：００～ＡＭ４：００<BREAK>におこしください",
			"\f"
		]
	},
	{
		"Index": 4,
		"JPN": [
			"えいぎょう{時間|じかん}<BREAK>ＡＭ９：００～ＡＭ０：００<BREAK>におこしください",
			"\f"
		]
	},
	{
		"Index": 5,
		"JPN": [
			"えいぎょう{時間|じかん}<BREAK>ＡＭ９：００～ＡＭ０：００<BREAK>におこしください",
			"\f"
		]
	},
	{
		"Index": 6,
		"JPN": [
			"えいぎょう{時間|じかん}<BREAK>ＡＭ９：００～ＡＭ０：００<BREAK>におこしください",
			"\f"
		]
	},
	{
		"Index": 7,
		"JPN": [
			"えいぎょう{時間|じかん}<BREAK>ＡＭ９：００～ＡＭ０：００<BREAK>におこしください",
			"\f"
		]
	},
	{
		"Index": 8,
		"JPN": [
			"{女子|じょし}トイレは　となりですよ",
			"\f"
		]
	},
	{
		"Index": 9,
		"JPN": [
			"{男子|だんし}トイレは　となりですよ",
			"\f"
		]
	},
	{
		"Index": 14,
		"JPN": [
			"ぐあいがわるいみたいだ",
			"{通信中|つうしんちゅう}は<BREAK>くすりをあげられないので",
			"{通信|つうしん}をきってから<BREAK>また　{話|はなし}を{聞|き}いてみよう",
			"\f"
		]
	},
	{
		"Index": 15,
		"JPN": [
			"ぐあいがわるいみたいだ",
			"くすりをあげますか？",
			"<CMD>138027002895</CMD>",
			"\f"
		]
	},
	{
		"Index": 16,
		"JPN": [
			"<CMD>3780</CMD>",
			"くすりをあげる<CMD>13802700ffff</CMD>",
			"あげなくていい<CMD>13802700ffff</CMD>",
			"\f"
		]
	},
	{
		"Index": 20,
		"JPN": [
			"ばっちり！<BREAK>じょうずに　まぜられたよ！",
			"\f"
		]
	},
	{
		"Index": 21,
		"JPN": [
			"うまく　まぜられたよ！",
			"\f"
		]
	},
	{
		"Index": 22,
		"JPN": [
			"ばっちり！<BREAK>じょうずに　やけたよ！",
			"\f"
		]
	},
	{
		"Index": 23,
		"JPN": [
			"うまく　やけたよ！",
			"\f"
		]
	},
	{
		"Index": 24,
		"JPN": [
			"じょうずに　にこめたよ！",
			"\f"
		]
	},
	{
		"Index": 25,
		"JPN": [
			"あまりおいしく　にこめなかった…",
			"\f"
		]
	},
	{
		"Index": 26,
		"JPN": [
			"しっかり　ひやせた！",
			"\f"
		]
	},
	{
		"Index": 27,
		"JPN": [
			"ひやしすぎちゃったみたい…",
			"\f"
		]
	},
	{
		"Index": 28,
		"JPN": [
			"ばっちり！<BREAK>じょうずに　やけたよ！",
			"\f"
		]
	},
	{
		"Index": 29,
		"JPN": [
			"うまく　やけたよ！",
			"\f"
		]
	},
	{
		"Index": 30,
		"JPN": [
			"ばっちり！<BREAK>カラッと　あげれたよ！",
			"\f"
		]
	},
	{
		"Index": 31,
		"JPN": [
			"うまく　あげれたよ！",
			"\f"
		]
	},
	{
		"Index": 32,
		"JPN": [
			"あまりうまく　やけなかった…",
			"\f"
		]
	},
	{
		"Index": 33,
		"JPN": [
			"しっぱいした",
			"\f"
		]
	},
	{
		"Index": 34,
		"JPN": [
			"せいこうした",
			"\f"
		]
	},
	{
		"Index": 35,
		"JPN": [
			"しっぱいした",
			"\f"
		]
	},
	{
		"Index": 36,
		"JPN": [
			"<CMD>058227006380</CMD>が<BREAK>かんせいした！",
			"\f"
		]
	},
	{
		"Index": 37,
		"JPN": [
			"<CMD>058227006380</CMD>が<BREAK>かんせいした！",
			"\f"
		]
	},
	{
		"Index": 38,
		"JPN": [
			"<CMD>008027000480</CMD>しっぱいりょうり<CMD>008027000180</CMD>が<BREAK>できてしまった…",
			"\f"
		]
	},
	{
		"Index": 39,
		"JPN": [
			"<CMD>058227006380</CMD>に<BREAK>あたらしく　なまえをつけますか？",
			"<CMD>138027004095</CMD>",
			"\f"
		]
	},
	{
		"Index": 40,
		"JPN": [
			"<CMD>3780</CMD>",
			"はい<CMD>13802700ffff</CMD>",
			"いいえ<CMD>13802700ffff</CMD>",
			"\f"
		]
	},
	{
		"Index": 41,
		"JPN": [
			"<CMD>058227006380</CMD>を<BREAK>どうしますか？",
			"<CMD>138027004295</CMD>",
			"\f"
		]
	},
	{
		"Index": 42,
		"JPN": [
			"<CMD>3780</CMD>",
			"じぶんでもつ<CMD>13802700ffff</CMD>",
			"そうこにいれる<CMD>13802700ffff</CMD>",
			"\f"
		]
	},
	{
		"Index": 43,
		"JPN": [
			"そうこがいっぱいです",
			"そうこの　なかを<BREAK>せいりしてください",
			"\f"
		]
	},
	{
		"Index": 44,
		"JPN": [
			"もちものが　いっぱいなので<BREAK>そうこに　しまいます",
			"\f"
		]
	},
	{
		"Index": 45,
		"JPN": [
			"もちものがいっぱいです",
			"そうこも　いっぱいなので<BREAK>そうこを　せいりしてください",
			"\f"
		]
	},
	{
		"Index": 46,
		"JPN": [
			"そうこに　<CMD>058227006380</CMD>を<BREAK>しまいます",
			"\f"
		]
	},
	{
		"Index": 47,
		"JPN": [
			"ざいりょうが<BREAK>ダメになってしまった…",
			"ざいりょうを　えらぶところから<BREAK>やりなおしますか？",
			"<CMD>138027004895</CMD>",
			"\f"
		]
	},
	{
		"Index": 48,
		"JPN": [
			"<CMD>3780</CMD>",
			"やりなおす<CMD>13802700ffff</CMD>",
			"やめる<CMD>13802700ffff</CMD>",
			"\f"
		]
	},
	{
		"Index": 49,
		"JPN": [
			"ざいりょうを　えらんでください",
			"\f"
		]
	},
	{
		"Index": 50,
		"JPN": [
			"もういちど　しょうひんづくりに<BREAK>ちょうせんしましょう！",
			"\f"
		]
	},
	{
		"Index": 51,
		"JPN": [
			"しょうひんを　つくるのを<BREAK>ちゅうしします",
			"\f"
		]
	},
	{
		"Index": 52,
		"JPN": [
			"ざいりょうが<BREAK>ダメになってしまったので　",
			"しょうひんを　つくるのを<BREAK>ちゅうしします",
			"\f"
		]
	},
	{
		"Index": 53,
		"JPN": [
			"いんしょくメニューをひらきます",
			"\f"
		]
	},
	{
		"Index": 54,
		"JPN": [
			"ばっちり！<BREAK>おいしく　にこめたよ！",
			"\f"
		]
	},
	{
		"Index": 55,
		"JPN": [
			"ざんねん<BREAK>りょうりに　しっぱいしちゃった…",
			"\f"
		]
	},
	{
		"Index": 56,
		"JPN": [
			"あまりうまく　やけなかった…",
			"\f"
		]
	},
	{
		"Index": 57,
		"JPN": [
			"あまりうまく　まぜられなかった…",
			"\f"
		]
	},
	{
		"Index": 58,
		"JPN": [
			"あまりうまく　あげれなかった…",
			"\f"
		]
	},
	{
		"Index": 60,
		"JPN": [
			"ちょっと　ゆっくりしすぎかも？<BREAK>さいしょは　もうすこしはやめに<BREAK>タッチペンを　まわしてみよう",
			"\f"
		]
	},
	{
		"Index": 61,
		"JPN": [
			"さいしょに　はやくまぜすぎると<BREAK>スピードを　もどすのが<BREAK>むずかしいよ",
			"バイトねこが　うたうくらいの<BREAK>はやさで　もうすこし<BREAK>ゆっくり　まぜてみよう",
			"\f"
		]
	},
	{
		"Index": 65,
		"JPN": [
			"タッチするのが　はやすぎたみたい<BREAK>ざいりょうが　よくやけるまで<BREAK>まってからとめてみよう",
			"\f"
		]
	},
	{
		"Index": 66,
		"JPN": [
			"タッチするのが　おそすぎたみたい<BREAK>ざいりょうが　ちょうどよく<BREAK>やけてるところで　とめてみよう",
			"\f"
		]
	},
	{
		"Index": 68,
		"JPN": [
			"ナベがこげないように<BREAK>やさしくナベを　かきまぜよう！",
			"\f"
		]
	},
	{
		"Index": 69,
		"JPN": [
			"ナベにアクがでたら<BREAK>すばやくアクを　とりのぞこう！",
			"\f"
		]
	},
	{
		"Index": 70,
		"JPN": [
			"あまり　まぜすぎると<BREAK>ざいりょうがフライパンから<BREAK>とびでてしまうので　ちゅうい！",
			"\f"
		]
	},
	{
		"Index": 71,
		"JPN": [
			"ざいりょうが　こげないように<BREAK>フライパンをかえしたり<BREAK>まぜたり　してみよう！",
			"\f"
		]
	},
	{
		"Index": 72,
		"JPN": [
			"あげものの　いろをよくみて<BREAK>コゲすぎるまえに<BREAK>すばやくナベから　とりだそう",
			"\f"
		]
	},
	{
		"Index": 73,
		"JPN": [
			"のこりじかんに　ちゅういして<BREAK>せんをなぞって　リボンを<BREAK>さいごまで　むすんでみよう！",
			"\f"
		]
	},
	{
		"Index": 74,
		"JPN": [
			"{火|ひ}をつけたら<BREAK>スイッチを　{左右|さゆう}にいどうさせて<BREAK>{火|ひ}かげんを　ちょうせいしよう！",
			"\f"
		]
	},
	{
		"Index": 75,
		"JPN": [
			"おんどがたかすぎたので<BREAK>{火|ひ}かげんに　きをつけよう！",
			"\f"
		]
	},
	{
		"Index": 76,
		"JPN": [
			"ちょうどいい　{火|ひ}かげんに<BREAK>ちょうせつして<BREAK>うまく　こうすいをつくろう！",
			"\f"
		]
	},
	{
		"Index": 77,
		"JPN": [
			"おんどがたかすぎたので<BREAK>{火|ひ}かげんに　きをつけよう！",
			"\f"
		]
	},
	{
		"Index": 78,
		"JPN": [
			"ちょうどいい　{火|ひ}かげんに<BREAK>ちょうせつして<BREAK>うまく　おちゃをつくろう！",
			"\f"
		]
	},
	{
		"Index": 79,
		"JPN": [
			"{布|ぬの}から　はみだしちゃった<BREAK>そとのわくから<BREAK>はみださないように　ぬってみよう",
			"\f"
		]
	},
	{
		"Index": 80,
		"JPN": [
			"のこりじかんに　ちゅういして<BREAK>さいごまで{布|ぬの}を　ぬってみよう！",
			"\f"
		]
	},
	{
		"Index": 81,
		"JPN": [
			"あげものの　いろをよくみて<BREAK>こんがり　あがるまでまってから<BREAK>ナベから　とりだそう！",
			"\f"
		]
	},
	{
		"Index": 82,
		"JPN": [
			"ナベにざいりょうを　いれたあと<BREAK>あげものからでているアワが<BREAK>よわくなってきて",
			"ざいりょうの　いろが<BREAK>こんがり　キツネいろにかわったら<BREAK>ナベから　とりだそう！",
			"\f"
		]
	},
	{
		"Index": 83,
		"JPN": [
			"すばやく　じかんないに<BREAK>キレイに　みがいてみよう！",
			"\f"
		]
	},
	{
		"Index": 84,
		"JPN": [
			"ちょうどいい　{火|ひ}かげんに<BREAK>ちょうせつして<BREAK>うまく　インクをつくろう！",
			"\f"
		]
	},
	{
		"Index": 85,
		"JPN": [
			"ばっちり！<BREAK>じょうずに　もりつけれたよ！",
			"\f"
		]
	},
	{
		"Index": 86,
		"JPN": [
			"ばっちり！<BREAK>じょうずに　トッピングできたよ！",
			"\f"
		]
	},
	{
		"Index": 87,
		"JPN": [
			"キレイなみために<BREAK>しあがったよ！",
			"\f"
		]
	},
	{
		"Index": 88,
		"JPN": [
			"ちょっとみためが<BREAK>こせいてき　だね…",
			"\f"
		]
	},
	{
		"Index": 89,
		"JPN": [
			"さらのうえにある<BREAK>ざいりょうをナベにいれて<BREAK>ざいりょうを　こんがりあげよう！",
			"\f"
		]
	},
	{
		"Index": 90,
		"JPN": [
			"のこりじかんに　ちゅういして<BREAK>せんをなぞって　はなを<BREAK>さいごまで　つつんでみよう！",
			"\f"
		]
	},
	{
		"Index": 93,
		"JPN": [
			"つうしん{中|ちゅう}は<BREAK>{開店前|かいてんまえ}の　お{店|みせ}には<BREAK>{入|はい}れません",
			"\f"
		]
	},
	{
		"Index": 94,
		"JPN": [
			"まだ<BREAK>お{店|みせ}が　{開|ひら}かれていません",
			"\f"
		]
	}
]