[
	{
		"Index": 0,
		"JPN": [
			"<CMD>18802700729b27000680</CMD><CMD>17802700729b2700088027000a8027000180</CMD><CMD>16802700729b27007e81</CMD>おまえらについて　おもしろい<BREAK>{話|はなし}が{広|ひろ}まってる<CMD>ff8127000280</CMD>",
			"\f"
		]
	},
	{
		"Index": 1,
		"JPN": [
			"{恋人|こいびと}を　{取|と}り{合|あ}って　しょうぶ<BREAK>してるって　{本当|ほんとう}<CMD>ff8127000180</CMD>？",
			"\f"
		]
	},
	{
		"Index": 2,
		"JPN": [
			"{恋人|こいびと}を{取|と}り{合|あ}って　あらそう<BREAK>なんて　なんだかかっこいいぜ<BREAK><CMD>028227000080</CMD>も　やってみたい<CMD>ff8127000280</CMD>",
			"\f"
		]
	},
	{
		"Index": 5,
		"JPN": [
			"おまえらについて　おもしろい<BREAK>{話|はなし}が　{広|ひろ}まってる<CMD>ff8127000280</CMD>",
			"\f"
		]
	},
	{
		"Index": 6,
		"JPN": [
			"{実|じつ}は　いいなずけ<BREAK>どうし<CMD>ff8127000180</CMD>？",
			"\f"
		]
	},
	{
		"Index": 7,
		"JPN": [
			"<CMD>18802700729b27000680</CMD><CMD>17802700729b2700088027000a8027000180</CMD><CMD>16802700729b27007e81</CMD>おまえらは　それでいいのかよ<BREAK>{相手|あいて}がきめられた　ケッコン<BREAK>なんて…",
			"<CMD>028227000080</CMD>　だったら<BREAK>おことわり<CMD>ff8127000080</CMD>",
			"\f"
		]
	},
	{
		"Index": 10,
		"JPN": [
			"おまえらについて　おもしろい<BREAK>{話|はなし}が{広|ひろ}まってる<CMD>ff8127000280</CMD>",
			"\f"
		]
	},
	{
		"Index": 11,
		"JPN": [
			"さいきん　{虫取|ムシと}りで<BREAK>プライドをかけて　しょうぶを<BREAK>してる<CMD>ff8127000380</CMD>？",
			"\f"
		]
	},
	{
		"Index": 12,
		"JPN": [
			"プライドをかけた　しょうぶ…<BREAK>なんだか　すごくかっこいいぞ<BREAK><CMD>028227000080</CMD>も　かけてみたい<CMD>ff8127000280</CMD>",
			"\f"
		]
	},
	{
		"Index": 15,
		"JPN": [
			"おまえらについて　おもしろい<BREAK>{話|はなし}が{広|ひろ}まってる<CMD>ff8127000280</CMD>",
			"\f"
		]
	},
	{
		"Index": 16,
		"JPN": [
			"さいきん　つりで<BREAK>プライドをかけて　しょうぶを<BREAK>してる<CMD>ff8127000380</CMD>？",
			"\f"
		]
	},
	{
		"Index": 17,
		"JPN": [
			"プライドをかけた　しょうぶ…<BREAK>なんだか　すごくかっこいいぞ<BREAK><CMD>028227000080</CMD>も　かけてみたい<CMD>ff8127000280</CMD>",
			"\f"
		]
	},
	{
		"Index": 20,
		"JPN": [
			"おまえらについて　おもしろい<BREAK>{話|はなし}が　{広|ひろ}まってる<CMD>ff8127000280</CMD>",
			"\f"
		]
	},
	{
		"Index": 21,
		"JPN": [
			"なかがよすぎて　まんざいコンビを<BREAK>けっせい　するんじゃ　ないかって<BREAK>{話|はなし}になってる<CMD>ff8127000280</CMD>",
			"\f"
		]
	},
	{
		"Index": 22,
		"JPN": [
			"おうえん　するからよ<BREAK>がんばって　ゆうめいに　なって<BREAK><CMD>028227000080</CMD>に　サインを<CMD>ff8127000480</CMD>",
			"\f"
		]
	},
	{
		"Index": 25,
		"JPN": [
			"<CMD>18802700729b27000680</CMD><CMD>17802700729b2700088027000a8027000180</CMD><CMD>16802700729b27007e81</CMD>おまえらについて　おもしろい<BREAK>{話|はなし}が　{広|ひろ}まってる<CMD>ff8127000280</CMD>",
			"\f"
		]
	},
	{
		"Index": 26,
		"JPN": [
			"さいきん　おまえたち<BREAK>なかいいよな　{実|じつ}はいきわかれの<BREAK>きょうだい　なんじゃないかって…",
			"\f"
		]
	},
	{
		"Index": 27,
		"JPN": [
			"もっぱらの　ウワサに<BREAK>なってる<CMD>ff8127000280</CMD>",
			"いきわかれの　きょうだいでも<BREAK>きょうだいが　いるって<BREAK>いいこと<CMD>ff8127000080</CMD>",
			"\f"
		]
	},
	{
		"Index": 30,
		"JPN": [
			"おまえらについて　おもしろい<BREAK>{話|はなし}が　{広|ひろ}まってる<CMD>ff8127000280</CMD>",
			"\f"
		]
	},
	{
		"Index": 31,
		"JPN": [
			"いつも　いっしょに　いるから<BREAK>いっしょに　{住|す}んじゃう<BREAK>んじゃないかって　ウワサ<CMD>ff8127000080</CMD>",
			"\f"
		]
	},
	{
		"Index": 32,
		"JPN": [
			"<CMD>18802700729b27000680</CMD><CMD>17802700729b2700088027000a8027000180</CMD><CMD>16802700729b27007e81</CMD>いっしょに{住|す}むって　きっと<BREAK>{楽|たの}しいだろうな　{話|はな}したいとき<BREAK>{話|はな}し{相手|あいて}にこまらないだろ",
			"\f"
		]
	},
	{
		"Index": 35,
		"JPN": [
			"おまえらについて　おもしろい<BREAK>{話|はなし}が{広|ひろ}まってる<CMD>ff8127000280</CMD>",
			"\f"
		]
	},
	{
		"Index": 36,
		"JPN": [
			"なかがいいのは　いいんだけど<BREAK>ヘンに　なかよすぎるんじゃないか<BREAK>って　ウワサになってる<CMD>ff8127000280</CMD>",
			"\f"
		]
	},
	{
		"Index": 37,
		"JPN": [
			"おまえら　まわりには　なかが<BREAK>いいように　みせかけて　{実|じつ}は<BREAK>ライバルなんじゃ　ないのか",
			"\f"
		]
	},
	{
		"Index": 40,
		"JPN": [
			"おまえらについて　おもしろい<BREAK>{話|はなし}が{広|ひろ}まってる<CMD>ff8127000280</CMD>",
			"\f"
		]
	},
	{
		"Index": 41,
		"JPN": [
			"おまえ　<CMD>f7812700839f</CMD>としか<BREAK>{遊|あそ}ばないんじゃないかって<BREAK>ウワサが　{流|なが}れてる<CMD>ff8127000280</CMD>",
			"\f"
		]
	},
	{
		"Index": 42,
		"JPN": [
			"いくら　だいすきだからって<BREAK>たまには　ほかのヤツとも<BREAK>{遊|あそ}ぼうぜ",
			"\f"
		]
	},
	{
		"Index": 45,
		"JPN": [
			"<CMD>18802700729b27000680</CMD><CMD>17802700729b2700088027000a8027000180</CMD><CMD>16802700729b27007e81</CMD>まえから　あやしいと<BREAK>{思|おも}ってたんだけど…",
			"\f"
		]
	},
	{
		"Index": 46,
		"JPN": [
			"ふうふゲンカのすえに<BREAK>ふられた<CMD>ff8127000380</CMD>？",
			"\f"
		]
	},
	{
		"Index": 47,
		"JPN": [
			"みんなが　おまえをせめても<BREAK><CMD>028227000080</CMD>は　おまえの<BREAK>みかた<CMD>ff8127000080</CMD>",
			"\f"
		]
	},
	{
		"Index": 50,
		"JPN": [
			"<CMD>18802700729b27000680</CMD><CMD>17802700729b2700088027000a8027000180</CMD><CMD>16802700729b27007e81</CMD>まえから　あやしいと<BREAK>{思|おも}ってたんだけど…",
			"\f"
		]
	},
	{
		"Index": 51,
		"JPN": [
			"しつれんのすえに　しょうしん<BREAK>りょこうにでも　{出|で}るんじゃないか<BREAK>って　{話|はなし}になってる<CMD>ff8127000280</CMD>",
			"\f"
		]
	},
	{
		"Index": 52,
		"JPN": [
			"{何|なに}かに　なやんでるんだったら<BREAK><CMD>028227000080</CMD>に　{話|はな}してくれよ<BREAK>そうだんにのるからよ",
			"\f"
		]
	},
	{
		"Index": 55,
		"JPN": [
			"まえから　あやしいと<BREAK>{思|おも}ってたんだけど…",
			"\f"
		]
	},
	{
		"Index": 56,
		"JPN": [
			"おまえが　{今度|こんど}<BREAK>{転校|てんこう}するんじゃないかって<BREAK>{話|はなし}になってるんだ",
			"\f"
		]
	},
	{
		"Index": 57,
		"JPN": [
			"<CMD>18802700729b27000680</CMD><CMD>17802700729b2700088027000a8027000180</CMD><CMD>16802700729b27007e81</CMD><CMD>028227000080</CMD>は　{引|ひ}きとめたり<BREAK>しないぜ　それぞれの{道|みち}は<BREAK>それぞれが　えらぶものだからな",
			"\f"
		]
	},
	{
		"Index": 60,
		"JPN": [
			"まえから　あやしいと<BREAK>{思|おも}ってたんだけど…",
			"\f"
		]
	},
	{
		"Index": 61,
		"JPN": [
			"{世界|せかい}せいふくの　おまじないを<BREAK>しているって　ウワサが<BREAK>{流|なが}れてる<CMD>ff8127000280</CMD>",
			"\f"
		]
	},
	{
		"Index": 62,
		"JPN": [
			"{世界|せかい}せいふくした　あかつきには<BREAK>この　<CMD>028227000080</CMD>を　なかまに<BREAK>いれてくれよな",
			"\f"
		]
	},
	{
		"Index": 65,
		"JPN": [
			"まえから　あやしいと<BREAK>{思|おも}ってたんだけど…",
			"\f"
		]
	},
	{
		"Index": 66,
		"JPN": [
			"<CMD>18802700729b27000680</CMD><CMD>17802700729b2700088027000a8027000180</CMD><CMD>16802700729b27007e81</CMD>{実|じつ}は　おまえが<BREAK>うちゅう{人|じん}って　いう<BREAK>ウワサが{流|なが}れてる<CMD>ff8127000280</CMD>",
			"\f"
		]
	},
	{
		"Index": 67,
		"JPN": [
			"<CMD>18802700729b27000180</CMD><CMD>17802700729b2700ad802700068027000280</CMD><CMD>16802700729b27005581</CMD>{一度|１ど}で　いいから　<CMD>028227000080</CMD>を<BREAK>うちゅうにつれていってくれ<BREAK>いつでもいいからよ",
			"\f"
		]
	},
	{
		"Index": 70,
		"JPN": [
			"まえから　あやしいと<BREAK>{思|おも}ってたんだけど…",
			"\f"
		]
	},
	{
		"Index": 71,
		"JPN": [
			"{今|いま}　おまえに　オバケが<BREAK>のりうつっているって<BREAK>{話|はなし}が{流|なが}れててさ",
			"\f"
		]
	},
	{
		"Index": 72,
		"JPN": [
			"おまえ　オバケじゃないよな？<BREAK>おまえが　おばけだったら<BREAK><CMD>028227000080</CMD>は　{友|とも}だちやめるぞ",
			"\f"
		]
	},
	{
		"Index": 75,
		"JPN": [
			"<CMD>18802700729b27000080</CMD><CMD>17802700729b2700b28027000a8027000180</CMD><CMD>16802700729b27006981</CMD>おまえ…　{何|なに}か<BREAK>かくしごとが　あるんだって？",
			"\f"
		]
	},
	{
		"Index": 76,
		"JPN": [
			"{実|じつ}は　おまえが　せいぎのヒーロー<BREAK>なんじゃないかって　ウワサが<BREAK>{流|なが}れてる<CMD>ff8127000280</CMD>",
			"\f"
		]
	},
	{
		"Index": 77,
		"JPN": [
			"たのむから　<CMD>028227000080</CMD>が<BREAK>イタズラしたときは<BREAK>みのがしてくれよな",
			"\f"
		]
	},
	{
		"Index": 80,
		"JPN": [
			"おまえ…　{何|なに}か<BREAK>かくしごとが　あるんだって？",
			"\f"
		]
	},
	{
		"Index": 81,
		"JPN": [
			"{実|じつ}は　おまえが　この{学校|がっこう}の<BREAK>{先生|せんせい}に　{恋|こい}してるって<BREAK>ウワサが{流|なが}れてるんだが…",
			"\f"
		]
	},
	{
		"Index": 82,
		"JPN": [
			"<CMD>18802700729b27000180</CMD><CMD>17802700729b2700ad802700068027000280</CMD><CMD>16802700729b27005581</CMD>{人|ひと}をすきに　なるのは<BREAK>じゆうだからよ　<CMD>028227000080</CMD>は<BREAK>おうえんする<CMD>ff8127000280</CMD>",
			"\f"
		]
	},
	{
		"Index": 85,
		"JPN": [
			"おまえ…　{何|なに}か<BREAK>かくしごとが<BREAK>あるんだって？",
			"\f"
		]
	},
	{
		"Index": 86,
		"JPN": [
			"おまえ　{実|じつ}は<BREAK>{虫|ムシ}なんじゃないかって<BREAK>ウワサが{流|なが}れてる<CMD>ff8127000280</CMD>",
			"\f"
		]
	},
	{
		"Index": 87,
		"JPN": [
			"べつにおまえが　バッタだろうと<BREAK>クモだろうと　<CMD>028227000080</CMD>と<BREAK>おまえは{友|とも}だち<CMD>ff8127000080</CMD>",
			"\f"
		]
	},
	{
		"Index": 90,
		"JPN": [
			"おまえ…　{何|なに}か<BREAK>かくしごとが　あるんだって？",
			"\f"
		]
	},
	{
		"Index": 91,
		"JPN": [
			"<CMD>18802700729b27000780</CMD><CMD>17802700729b2700b18027000a8027000180</CMD>{実|じつ}は　おまえがねぼけたまま<BREAK>ウロウロして　{川|かわ}に{落|お}ちた<BREAK>って　ウワサが{流|なが}れてる<CMD>ff8127000280</CMD>",
			"\f"
		]
	},
	{
		"Index": 92,
		"JPN": [
			"つらいことでもあったのか？<BREAK>いつでも<CMD>028227000080</CMD>が<BREAK>そうだんにのるぞ",
			"\f"
		]
	},
	{
		"Index": 95,
		"JPN": [
			"<CMD>18802700729b27000080</CMD><CMD>17802700729b2700b28027000a8027000180</CMD><CMD>16802700729b27006981</CMD>おまえ…　{何|なに}か<BREAK>かくしごとが<BREAK>あるんだって？",
			"\f"
		]
	},
	{
		"Index": 96,
		"JPN": [
			"{実|じつ}はおまえ<BREAK>すごいむっつりスケベだって<BREAK>{話|はなし}になってる<CMD>ff8127000280</CMD>",
			"\f"
		]
	},
	{
		"Index": 97,
		"JPN": [
			"みんなが　おまえをスケベ<BREAK>よばわりしても　<CMD>028227000080</CMD>だけは<BREAK>{友|とも}だちだからな",
			"\f"
		]
	}
]