[
	{
		"Index": 0,
		"JPN": [
			"すき",
			"あいしてる",
			"つきあって",
			"ありがとう",
			"らぶ",
			"いっしょ",
			"どきどき",
			"LOVE",
			"かっこいい",
			"かわいい",
			"きれい",
			"うつくしい",
			"すてき",
			"きゅーと",
			"すごい",
			"みなおした",
			"\f"
		]
	},
	{
		"Index": 1,
		"JPN": [
			"スキ",
			"アイシテル",
			"ツキアッテ",
			"アリガトウ",
			"ラブ",
			"イッショ",
			"ドキドキ",
			"LOVE",
			"カッコイイ",
			"カワイイ",
			"キレイ",
			"ウツクシイ",
			"ステキ",
			"キュート",
			"スゴイ",
			"ミナオシタ",
			"\f"
		]
	},
	{
		"Index": 2,
		"JPN": [
			"げんき",
			"がんば",
			"ふぁいと",
			"がっつ",
			"いいことある",
			"だいじょうぶ",
			"なぐさめ",
			"おうえん",
			"まけるな",
			"まけないで",
			"\f"
		]
	},
	{
		"Index": 3,
		"JPN": [
			"ゲンキ",
			"ガンバ",
			"ファイト",
			"ガッツ",
			"イイコトアル",
			"ダイジョウブ",
			"ナグサメ",
			"オウエン",
			"マケルナ",
			"マケナイデ",
			"\f"
		]
	},
	{
		"Index": 4,
		"JPN": [
			"おたんこなす",
			"たべちゃった",
			"むかつく",
			"きらい",
			"のろま",
			"ぐず",
			"ノータリン",
			"ぶさいく",
			"ぶす",
			"まぬけ",
			"でべそ",
			"ばーか",
			"\f"
		]
	},
	{
		"Index": 5,
		"JPN": [
			"オタンコナス",
			"タベチャッタ",
			"ムカツク",
			"キライ",
			"ノロマ",
			"グズ",
			"トンマ",
			"ブサイク",
			"ブス",
			"マヌケ",
			"デベソ",
			"バーカ",
			"\f"
		]
	}
]