[
	{
		"Index": 0,
		"JPN": [
			"<CMD>18802700729b27000080</CMD><CMD>17802700729b2700b28027000a8027000180</CMD><CMD>16802700729b27006981</CMD>あら　ちょうど<BREAK><CMD>3a8227000080</CMD><BREAK><CMD>ff8127000180</CMD>？",
			"それにかんけいした{物|もの}が<BREAK>ほしかったところだから<BREAK>ありがたい<CMD>ff8127000280</CMD>",
			"\f"
		]
	},
	{
		"Index": 1,
		"JPN": [
			"<CMD>18802700729b27000580</CMD><CMD>17802700729b2700aa8027000a8027000180</CMD><CMD>16802700729b27002d81</CMD>ええと…<BREAK>どこに{行|い}くのがいいか<BREAK>まよってしまう<CMD>ff8127000280</CMD>",
			"どこに{何|なに}があるのか<BREAK>しっかりかくにんしないと<BREAK>いけない<CMD>ff8127000280</CMD>",
			"\f"
		]
	},
	{
		"Index": 2,
		"JPN": [
			"こんなにいろいろな<BREAK>お{店|みせ}や　せつびがあると…",
			"<CMD>18802700729b27000180</CMD><CMD>17802700729b2700ad802700068027000280</CMD><CMD>16802700729b27005581</CMD>これから<BREAK>どこにいくのいいか<BREAK>まよってしまう<CMD>ff8127000280</CMD>",
			"\f"
		]
	},
	{
		"Index": 3,
		"JPN": [
			"このモールは{広|ひろ}いので<BREAK>{見|み}ていない{場所|ばしょ}が<BREAK>まだまだ　たくさんある<CMD>ff8127000280</CMD>",
			"<CMD>18802700729b27000180</CMD><CMD>17802700729b2700ad802700068027000280</CMD><CMD>16802700729b27005581</CMD>どこにいっても<BREAK>しんせんな<BREAK>おどろきがある<CMD>ff8127000280</CMD>",
			"\f"
		]
	},
	{
		"Index": 4,
		"JPN": [
			"<CMD>18802700729b27000380</CMD><CMD>17802700729b2700ab8027000a8027000180</CMD><CMD>16802700729b27003081</CMD>あんまり{広|ひろ}いので<BREAK><CMD>028227000080</CMD>　{少々|しょうしょう}<BREAK>つかれてしまった<CMD>ff8127000280</CMD>",
			"ここで　{少|すこ}しだけ<BREAK>{休|やす}んでいくことにする<CMD>ff8127000280</CMD>",
			"\f"
		]
	},
	{
		"Index": 5,
		"JPN": [
			"このモールは<BREAK>{広々|ひろびろ}としているのが<BREAK>よろしい<CMD>ff8127000280</CMD>",
			"<CMD>18802700729b27000180</CMD><CMD>17802700729b270001802700048027000180</CMD><CMD>16802700729b27004181</CMD>とても<CMD>028227000080</CMD>の<BREAK>このみ<CMD>ff8127000080</CMD>",
			"\f"
		]
	},
	{
		"Index": 6,
		"JPN": [
			"そんなにおなかが<BREAK>すいているわけでは<BREAK>ないのだけれど…",
			"<CMD>18802700729b27000180</CMD><CMD>17802700729b2700ad802700068027000280</CMD><CMD>16802700729b27005581</CMD>ちょっとここで<BREAK>{食事|しょくじ}をしていくのも<BREAK>いいかもしれない<CMD>ff8127000280</CMD>",
			"\f"
		]
	},
	{
		"Index": 7,
		"JPN": [
			"ふう　ちょうど<BREAK>つかれたなあって<BREAK>{思|おも}っていたところ<CMD>ff8127000080</CMD>",
			"<CMD>18802700729b27000180</CMD><CMD>17802700729b270001802700048027000180</CMD><CMD>16802700729b27004181</CMD>{休|やす}める{場所|ばしょ}があって<BREAK>とても{助|たす}かった<CMD>ff8127000280</CMD>",
			"\f"
		]
	},
	{
		"Index": 8,
		"JPN": [
			"<CMD>18802700729b27000180</CMD><CMD>17802700729b270001802700048027000180</CMD><CMD>16802700729b27004181</CMD><CMD>028227000080</CMD>　{味|あじ}には<BREAK>うるさい{方|ほう}だけど<BREAK>このりょうりはおいしい<CMD>ff8127000280</CMD>",
			"ここのシェフは<BREAK>なかなか<BREAK>すばらしい　うで<CMD>ff8127000080</CMD>",
			"\f"
		]
	},
	{
		"Index": 9,
		"JPN": [
			"たまには　こういう<BREAK>にぎやかなところで<BREAK>{食事|しょくじ}をするのも…",
			"<CMD>18802700729b27000180</CMD><CMD>17802700729b2700ad802700068027000280</CMD><CMD>16802700729b27005581</CMD>{楽|たの}しい{気分|きぶん}になって<BREAK>いいもの<CMD>ff8127000080</CMD>",
			"\f"
		]
	},
	{
		"Index": 10,
		"JPN": [
			"こういうところの{食事|しょくじ}って<BREAK>たいしたことないだろうと<BREAK>{思|おも}っていたけど…",
			"<CMD>18802700729b27000780</CMD><CMD>17802700729b2700b18027000a8027000180</CMD>そんなことない<CMD>ff8127000280</CMD><BREAK>とてもおいしい<BREAK>りょうりだった<CMD>ff8127000280</CMD>",
			"\f"
		]
	},
	{
		"Index": 11,
		"JPN": [
			"こういうところで{食事|しょくじ}を<BREAK>するのって　{落|お}ち{着|つ}かない<BREAK>かと{思|おも}っていたけど…",
			"<CMD>18802700729b27000180</CMD><CMD>17802700729b2700ad802700068027000280</CMD><CMD>16802700729b27005581</CMD>{意外|いがい}にゆっくりできて<BREAK>{落|お}ち{着|つ}く<CMD>ff8127000280</CMD>",
			"\f"
		]
	},
	{
		"Index": 12,
		"JPN": [
			"<CMD>18802700729b27000580</CMD><CMD>17802700729b2700af802700088027000180</CMD><CMD>16802700729b27005681</CMD>あら　これってなかなか<BREAK>インパクトのある<BREAK>オブジェ<CMD>ff8127000080</CMD>",
			"もっと{小|ちい}さければ<BREAK><CMD>028227000080</CMD>もこのオブジェ<BREAK>ほしい<CMD>ff8127000280</CMD>",
			"\f"
		]
	},
	{
		"Index": 13,
		"JPN": [
			"<CMD>18802700729b27000380</CMD><CMD>17802700729b2700ab8027000a8027000180</CMD><CMD>16802700729b27003081</CMD>うーん<BREAK>このオブジェも…<BREAK>{悪|わる}くはないけど…",
			"ここにおくのなら　もっと<BREAK>わかりやすいオブジェが<BREAK>いいと{思|おも}う<CMD>ff8127000280</CMD>",
			"\f"
		]
	},
	{
		"Index": 14,
		"JPN": [
			"<CMD>18802700729b27000180</CMD><CMD>17802700729b270001802700048027000180</CMD><CMD>16802700729b27004181</CMD>ここは　お{店|みせ}が<BREAK>たくさんあって<BREAK>{本当|ほんとう}にべんり<CMD>ff8127000080</CMD>",
			"{前|まえ}から　こういう{場所|ばしょ}が<BREAK>あればいいなと<BREAK>{思|おも}っていた<CMD>ff8127000280</CMD>",
			"\f"
		]
	},
	{
		"Index": 15,
		"JPN": [
			"ここでのショッピングは<BREAK>ホントに{楽|たの}しかった<CMD>ff8127000280</CMD>",
			"<CMD>18802700729b27000780</CMD><CMD>17802700729b2700b18027000a8027000180</CMD>あんまり{楽|たの}しかったので<BREAK>{今日|きょう}はちょっと<BREAK>{買|か}いすぎてしまった<CMD>ff8127000280</CMD>　",
			"\f"
		]
	},
	{
		"Index": 16,
		"JPN": [
			"<CMD>18802700729b27000080</CMD><CMD>17802700729b2700b28027000a8027000180</CMD><CMD>16802700729b27006981</CMD>この{先|さき}は<BREAK>{何|なに}をあつかう<BREAK>お{店|みせ}がある<CMD>ff8127000380</CMD>？",
			"{見|み}てまわるだけでも<BREAK>とっても<BREAK>ワクワクする<CMD>ff8127000280</CMD>",
			"\f"
		]
	},
	{
		"Index": 17,
		"JPN": [
			"もう{何|なに}があっても<BREAK>おどろかないと<BREAK>{思|おも}っていたけど…",
			"<CMD>18802700729b27000580</CMD><CMD>17802700729b2700af802700088027000180</CMD><CMD>16802700729b27005681</CMD>デパートまで　あるなんて<BREAK>おどろいた<CMD>ff8127000280</CMD><BREAK>ここはなんでもアリ<CMD>ff8127000180</CMD>？",
			"\f"
		]
	}
]