[
	{
		"Index": 1,
		"JPN": [
			"<CMD>3082</CMD>へ",
			"{夜|よる}ねむれない<CMD>ff8127000280</CMD><BREAK>なぜか　{目|め}がさえる<CMD>ff8127000280</CMD><BREAK>なんでな<CMD>ff8127000380</CMD>？",
			"<CMD>3182</CMD>より",
			"\f"
		]
	},
	{
		"Index": 2,
		"JPN": [
			"<CMD>3082</CMD>へ",
			"{足|あし}がつって　イタかった<CMD>ff8127000280</CMD><BREAK>{足|あし}がつるのは　つかれている<BREAK>ショウコな<CMD>ff8127000380</CMD>？",
			"<CMD>3182</CMD>より",
			"\f"
		]
	},
	{
		"Index": 3,
		"JPN": [
			"<CMD>3082</CMD>へ",
			"ムカついて　ついつい<BREAK>{食|た}べすぎちゃう<CMD>ff8127000280</CMD><BREAK>スッキリはしないけどね",
			"<CMD>3182</CMD>より",
			"\f"
		]
	},
	{
		"Index": 4,
		"JPN": [
			"<CMD>3082</CMD>へ",
			"{音|おと}が{気|き}になる<CMD>ff8127000280</CMD><BREAK>ちょっとした{音|おと}でも<BREAK>ビックリする<CMD>ff8127000280</CMD>",
			"<CMD>3182</CMD>より",
			"\f"
		]
	},
	{
		"Index": 5,
		"JPN": [
			"<CMD>3082</CMD>へ",
			"なんか　ムシャクシャしたんで<BREAK>いっぱい　{買|か}い{物|もの}した<CMD>ff8127000280</CMD><BREAK>でも　まだ{足|た}りない<CMD>ff8127000280</CMD>",
			"<CMD>3182</CMD>より",
			"\f"
		]
	},
	{
		"Index": 6,
		"JPN": [
			"<CMD>3082</CMD>へ",
			"だいじょうぶ<BREAK>ぜんぜん　だいじょうぶ<CMD>ff8127000080</CMD><BREAK>あんしんしてほしい<CMD>ff8127000280</CMD>",
			"<CMD>3182</CMD>より",
			"\f"
		]
	},
	{
		"Index": 7,
		"JPN": [
			"<CMD>3082</CMD>へ",
			"いやなコトがあった<CMD>ff8127000280</CMD><BREAK>とっても　おちこんだ<CMD>ff8127000280</CMD><BREAK>そんなことってない？",
			"<CMD>3182</CMD>より",
			"\f"
		]
	},
	{
		"Index": 8,
		"JPN": [
			"<CMD>3082</CMD>へ",
			"んー…………………<BREAK>……………………<BREAK>なんでもない<CMD>ff8127000280</CMD>",
			"<CMD>3182</CMD>より",
			"\f"
		]
	},
	{
		"Index": 9,
		"JPN": [
			"<CMD>3082</CMD>へ",
			"よく　わからないけど<BREAK>イライラする<CMD>ff8127000280</CMD><BREAK>どうして？",
			"<CMD>3182</CMD>より",
			"\f"
		]
	},
	{
		"Index": 10,
		"JPN": [
			"<CMD>3082</CMD>へ",
			"おちつきがないねって<BREAK>{言|い}われた<CMD>ff8127000280</CMD><BREAK>ショック<CMD>ff8127000080</CMD>！",
			"<CMD>3182</CMD>より",
			"\f"
		]
	},
	{
		"Index": 11,
		"JPN": [
			"<CMD>3082</CMD>へ",
			"なにか　おもしろいコトないかな<BREAK>なにをしても<BREAK>おもしろくない<CMD>ff8127000280</CMD>",
			"<CMD>3182</CMD>より",
			"\f"
		]
	},
	{
		"Index": 12,
		"JPN": [
			"<CMD>3082</CMD>へ",
			"イラついてたせいか<BREAK>ちょっとしたコトで<BREAK>おこっちゃった<CMD>ff8127000280</CMD>……<BREAK>はんせいしないとダメ<CMD>ff8127000180</CMD>",
			"<CMD>3182</CMD>より",
			"\f"
		]
	},
	{
		"Index": 21,
		"JPN": [
			"<CMD>3082</CMD>へ",
			"みせをひらいているみなに<BREAK>おうより　おふれがある<BREAK>いそいで　おうきゅうへ<BREAK>あつまるように",
			"<CMD>3182</CMD>より",
			"\f"
		]
	}
]